pylint_grandfather/__init__.py
pylint_grandfather/cli.py
pylint_grandfather/grandfather.py
pylint_grandfather-1.0.0.dist-info/DESCRIPTION.rst
pylint_grandfather-1.0.0.dist-info/METADATA
pylint_grandfather-1.0.0.dist-info/RECORD
pylint_grandfather-1.0.0.dist-info/WHEEL
pylint_grandfather-1.0.0.dist-info/entry_points.txt
pylint_grandfather-1.0.0.dist-info/metadata.json
pylint_grandfather-1.0.0.dist-info/top_level.txt
