Metadata-Version: 2.0
Name: pylint-grandfather
Version: 1.0.0
Summary: Grandfather in specific pylint failures
Home-page: https://github.com/jacob-meacham/pylint-grandfather
Author: Jacob Meacham
Author-email: jacob.e.meacham@gmail.com
License: UNKNOWN
Project-URL: Bug Reports, https://github.com/jacob-meacham/pylint-grandfather/issues
Project-URL: Source, https://github.com/jacob-meacham/pylint-grandfather/
Keywords: lint pylint
Platform: UNKNOWN
Classifier: Development Status :: 4 - Beta
Classifier: Intended Audience :: Developers
Classifier: Topic :: Software Development
Classifier: License :: OSI Approved :: MIT License
Classifier: Programming Language :: Python :: 3
Classifier: Programming Language :: Python :: 3.4
Classifier: Programming Language :: Python :: 3.5
Classifier: Programming Language :: Python :: 3.6
